jam_sdk/__init__.py
jam_sdk/constants.py
jam_sdk/example.py
jam_sdk/solver/__init__.py
jam_sdk/solver/base.py
jam_sdk/solver/solver_types.py
jam_sdk/utils.py
jam_sdk-0.10.0.dist-info/LICENSE
jam_sdk-0.10.0.dist-info/METADATA
jam_sdk-0.10.0.dist-info/WHEEL
jam_sdk-0.10.0.dist-info/RECORD
