Metadata-Version: 2.3
Name: jam_sdk
Version: 0.10.0
Summary: Bebop Jam SDK
Author: Bebop
Author-email: info@bebop.xyz
Requires-Python: >=3.11,<3.12
Classifier: Programming Language :: Python :: 3
Classifier: Programming Language :: Python :: 3.11
Requires-Dist: aiocache (==0.12.3)
Requires-Dist: eth-abi (==4.2.1)
Requires-Dist: eth-account (==0.11.2)
Requires-Dist: eth-typing (==3.5.2)
Requires-Dist: eth-utils (==4.1.1)
Requires-Dist: msgspec (==0.18.6)
Requires-Dist: pydantic (==2.9.2)
Requires-Dist: web3 (==6.19.0)
Requires-Dist: websockets (==14.2)
Project-URL: Documentation, https://github.com/bebop-dex/bebop-core
Project-URL: Repository, https://github.com/bebop-dex/bebop-core
